{
  "config": "M5 Macbook Pro",
  "engine": "Trino",
  "queries": [
    {
      "misEstimates": {
        "aggregate": {
          "+2x": 0,
          "+4x": 0,
          "+8x": 0,
          "-2x": 0,
          "-4x": 0,
          "-8x": 0,
          "<16x": 0,
          "=": 1,
          ">16x": 0
        },
        "distribute": {
          "+2x": 0,
          "+4x": 1,
          "+8x": 0,
          "-2x": 0,
          "-4x": 0,
          "-8x": 0,
          "<16x": 0,
          "=": 1,
          ">16x": 5
        },
        "filter": {
          "+2x": 0,
          "+4x": 0,
          "+8x": 0,
          "-2x": 0,
          "-4x": 0,
          "-8x": 0,
          "<16x": 0,
          "=": 1,
          ">16x": 5
        },
        "hash": {
          "+2x": 0,
          "+4x": 0,
          "+8x": 0,
          "-2x": 0,
          "-4x": 0,
          "-8x": 0,
          "<16x": 0,
          "=": 0,
          ">16x": 0
        },
        "join": {
          "+2x": 0,
          "+4x": 0,
          "+8x": 0,
          "-2x": 0,
          "-4x": 0,
          "-8x": 0,
          "<16x": 0,
          "=": 0,
          ">16x": 0
        },
        "scan": {
          "+2x": 0,
          "+4x": 1,
          "+8x": 0,
          "-2x": 0,
          "-4x": 0,
          "-8x": 0,
          "<16x": 0,
          "=": 2,
          ">16x": 6
        },
        "sort": {
          "+2x": 0,
          "+4x": 0,
          "+8x": 0,
          "-2x": 0,
          "-4x": 0,
          "-8x": 0,
          "<16x": 0,
          "=": 0,
          ">16x": 0
        }
      },
      "operatorRows": {
        "aggregate": 48,
        "distribute": 345491,
        "hash": 346072,
        "join": 1002,
        "scan": 345531,
        "seek": 0,
        "sort": 0
      },
      "plan": "Estimate    Actual  Operator\n       1         ∞  PROJECT min AS of_person, min_42 AS biography_movie\n       1         1  AGGREGATE MIN(min_43) AS min, MIN(min_44) AS min_42\n       -        16  DISTRIBUTE GATHER\n       -        16  AGGREGATE MIN(name_19) AS min_43, MIN(title) AS min_44\n       -        32  INNER JOIN HASH ON movie_id = id_35\n  265059    340186  │└DISTRIBUTE HASH ON id_35\n  265059    340186  │ PROJECT id AS id_35, title\n  265059    340186  │ FILTER production_year BETWEEN 1980 AND 1995\n  265059    340186  │ TABLE SCAN title\n       -       151  INNER JOIN HASH ON info_type_id = id_5\n     113         1  │└DISTRIBUTE GATHER\n     113         1  │ PROJECT id AS id_5\n     113         1  │ FILTER info = 'mini biography'\n     113         1  │ TABLE SCAN info_type\n       -       151  INNER JOIN HASH ON person_id_1 = person_id_29\n 2667298        64  │└DISTRIBUTE HASH ON person_id_29\n 2667298        64  │ PROJECT person_id AS person_id_29, info_type_id\n 2667298        64  │ FILTER note = 'Volker Boehm'\n 2667298        64  │ TABLE SCAN person_info\n       -       151  INNER JOIN HASH ON person_id_1 = id_18\n 3750742        17  │└DISTRIBUTE HASH ON id_18\n 3750742        17  │ PROJECT id AS id_18, name AS name_19\n 3750742        17  │ FILTER (gender IN('f','m')) AND (name_pcode_cf BETWEEN 'A' AND 'F') AND ((gender = 'm') OR ((gender = 'f') AND (name LIKE 'B%')))\n 3750742        17  │ TABLE SCAN name\n       -       151  INNER JOIN HASH ON link_type_id = id_9\n      18         1  │└DISTRIBUTE GATHER\n      18         1  │ PROJECT id AS id_9\n      18         1  │ FILTER link = 'features'\n      18         1  │ TABLE SCAN link_type\n       -       151  INNER JOIN HASH ON movie_id = linked_movie_id\n   29997      5186  │└DISTRIBUTE GATHER\n   29997      5186  │ TABLE SCAN movie_link\n       -        96  INNER JOIN HASH ON person_id_1 = person_id\n  811209        20  │└DISTRIBUTE GATHER\n  811209        20  │ FILTER name LIKE '%a%'\n  811209        20  │ TABLE SCAN aka_name\n36244344        56  PROJECT person_id AS person_id_1, movie_id\n36244344        56  TABLE SCAN cast_info\n",
      "sql": "SELECT MIN(n.name) AS of_person,\n       MIN(t.title) AS biography_movie\nFROM job.aka_name AS an,\n     job.cast_info AS ci,\n     job.info_type AS it,\n     job.link_type AS lt,\n     job.movie_link AS ml,\n     job.name AS n,\n     job.person_info AS pi,\n     job.title AS t\nWHERE an.name LIKE '%a%'\n  AND it.info ='mini biography'\n  AND lt.link ='features'\n  AND n.name_pcode_cf BETWEEN 'A' AND 'F'\n  AND (n.gender='m'\n       OR (n.gender = 'f'\n           AND n.name LIKE 'B%'))\n  AND pi.note ='Volker Boehm'\n  AND t.production_year BETWEEN 1980 AND 1995\n  AND n.id = an.person_id\n  AND n.id = pi.person_id\n  AND ci.person_id = n.id\n  AND t.id = ci.movie_id\n  AND ml.linked_movie_id = t.id\n  AND lt.id = ml.link_type_id\n  AND it.id = pi.info_type_id\n  AND pi.person_id = an.person_id\n  AND pi.person_id = ci.person_id\n  AND an.person_id = ci.person_id\n  AND ci.movie_id = ml.linked_movie_id;\n",
      "startTime": "2026-07-01T14:53:11.370601Z",
      "status": "OK",
      "timeMs": 448.911
    }
  ],
  "runtime": {
    "avgMs": 448.911,
    "bestMs": 448.911,
    "maxMs": 448.911,
    "minMs": 448.911,
    "stdDevMs": 0.0
  },
  "storageVariant": "iceberg",
  "theorem": {
    "categories": [
      "PLAN"
    ],
    "description": "Join Order Benchmark 7A Analysis",
    "displayName": "JOB-7A",
    "name": "PLAN-JOB-7A",
    "tags": [
      "IMDB",
      "JOB"
    ]
  },
  "version": "481"
}