{
  "engine": "PostgreSQL",
  "queries": [
    {
      "misEstimates": {
        "aggregate": {
          "+2x": 0,
          "+4x": 0,
          "+8x": 0,
          "-2x": 0,
          "-4x": 0,
          "-8x": 0,
          "<16x": 0,
          "=": 2,
          ">16x": 0
        },
        "filter": {
          "+2x": 0,
          "+4x": 0,
          "+8x": 0,
          "-2x": 0,
          "-4x": 0,
          "-8x": 0,
          "<16x": 0,
          "=": 0,
          ">16x": 0
        },
        "hash": {
          "+2x": 0,
          "+4x": 0,
          "+8x": 0,
          "-2x": 0,
          "-4x": 0,
          "-8x": 0,
          "<16x": 0,
          "=": 1,
          ">16x": 0
        },
        "join": {
          "+2x": 0,
          "+4x": 0,
          "+8x": 2,
          "-2x": 0,
          "-4x": 0,
          "-8x": 0,
          "<16x": 0,
          "=": 0,
          ">16x": 2
        },
        "scan": {
          "+2x": 0,
          "+4x": 0,
          "+8x": 0,
          "-2x": 0,
          "-4x": 0,
          "-8x": 0,
          "<16x": 1,
          "=": 6,
          ">16x": 0
        },
        "sort": {
          "+2x": 0,
          "+4x": 0,
          "+8x": 0,
          "-2x": 0,
          "-4x": 0,
          "-8x": 0,
          "<16x": 0,
          "=": 0,
          ">16x": 0
        }
      },
      "operatorRows": {
        "aggregate": 6,
        "distribute": 0,
        "hash": 10,
        "join": 24033,
        "scan": 24025,
        "seek": 0,
        "sort": 0
      },
      "plan": "Estimate    Actual  Operator\n       1         1  AGGREGATE MIN(title)\n       3         3  AGGREGATE PARTIAL MIN(title)\n      45         3  INNER JOIN LOOP ON id = info_type_id\n      45         3  │└INNER JOIN LOOP ON movie_id = id\n     132         3  │ │└INNER JOIN LOOP ON id = movie_id\n     110         0  │ │ │└INNER JOIN HASH ON company_type_id = id\n       1         1  │ │ │ │└TABLE SCAN company_type AS ct WHERE ct.kind = 'production companies'\n    1320     24024  │ │ │ TABLE SCAN movie_companies AS mc WHERE (mc.note LIKE '%(theatrical)%') AND (mc.note LIKE '%(France)%')\n       0         0  │ │ TABLE SEEK title AS t WHERE t.production_year > 2005\n       0         0  │ TABLE SEEK movie_info AS mi WHERE mi.info IN('Sweden','Norway','Germany','Denmark','Swedish','Denish','Norwegian','German')\n       0         0  TABLE SEEK info_type AS it\n",
      "sql": "SELECT MIN(t.title) AS typical_european_movie\nFROM job.company_type AS ct,\n     job.info_type AS it,\n     job.movie_companies AS mc,\n     job.movie_info AS mi,\n     job.title AS t\nWHERE ct.kind = 'production companies'\n  AND mc.note LIKE '%(theatrical)%'\n  AND mc.note LIKE '%(France)%'\n  AND mi.info IN ('Sweden',\n                  'Norway',\n                  'Germany',\n                  'Denmark',\n                  'Swedish',\n                  'Denish',\n                  'Norwegian',\n                  'German')\n  AND t.production_year > 2005\n  AND t.id = mi.movie_id\n  AND t.id = mc.movie_id\n  AND mc.movie_id = mi.movie_id\n  AND ct.id = mc.company_type_id\n  AND it.id = mi.info_type_id;\n",
      "startTime": "2026-06-17T12:32:35.830033Z",
      "status": "OK",
      "timeMs": 67.035
    }
  ],
  "runtime": {
    "avgMs": 67.035,
    "bestMs": 67.035,
    "maxMs": 67.035,
    "minMs": 67.035,
    "stdDevMs": 0.0
  },
  "storageVariant": "native",
  "theorem": {
    "categories": [
      "PLAN"
    ],
    "description": "Join Order Benchmark 5A Analysis",
    "displayName": "JOB-5A",
    "name": "JOB-5A",
    "tags": [
      "IMDB",
      "JOB"
    ]
  },
  "version": "18.2"
}