[
  {
    "Execution Time": 19914.976,
    "Plan": {
      "Actual Loops": 1,
      "Actual Rows": 1.0,
      "Actual Startup Time": 19914.846,
      "Actual Total Time": 19914.851,
      "Async Capable": false,
      "Disabled": false,
      "Local Dirtied Blocks": 0,
      "Local Hit Blocks": 0,
      "Local Read Blocks": 0,
      "Local Written Blocks": 0,
      "Node Type": "Aggregate",
      "Output": [
        "min(an.name)",
        "min(t.title)"
      ],
      "Parallel Aware": false,
      "Partial Mode": "Simple",
      "Plan Rows": 1,
      "Plan Width": 64,
      "Plans": [
        {
          "Actual Loops": 1,
          "Actual Rows": 3710592.0,
          "Actual Startup Time": 11.642,
          "Actual Total Time": 19596.779,
          "Async Capable": false,
          "Disabled": false,
          "Inner Unique": false,
          "Join Type": "Inner",
          "Local Dirtied Blocks": 0,
          "Local Hit Blocks": 0,
          "Local Read Blocks": 0,
          "Local Written Blocks": 0,
          "Node Type": "Nested Loop",
          "Output": [
            "an.name",
            "t.title"
          ],
          "Parallel Aware": false,
          "Parent Relationship": "Outer",
          "Plan Rows": 3376,
          "Plan Width": 33,
          "Plans": [
            {
              "Actual Loops": 1,
              "Actual Rows": 2832555.0,
              "Actual Startup Time": 11.634,
              "Actual Total Time": 15959.109,
              "Async Capable": false,
              "Disabled": false,
              "Inner Unique": true,
              "Join Type": "Inner",
              "Local Dirtied Blocks": 0,
              "Local Hit Blocks": 0,
              "Local Read Blocks": 0,
              "Local Written Blocks": 0,
              "Node Type": "Nested Loop",
              "Output": [
                "ci.person_id",
                "n.id",
                "t.title"
              ],
              "Parallel Aware": false,
              "Parent Relationship": "Outer",
              "Plan Rows": 1390,
              "Plan Width": 25,
              "Plans": [
                {
                  "Actual Loops": 1,
                  "Actual Rows": 2832555.0,
                  "Actual Startup Time": 11.546,
                  "Actual Total Time": 12838.343,
                  "Async Capable": false,
                  "Disabled": false,
                  "Inner Unique": false,
                  "Join Type": "Inner",
                  "Local Dirtied Blocks": 0,
                  "Local Hit Blocks": 0,
                  "Local Read Blocks": 0,
                  "Local Written Blocks": 0,
                  "Node Type": "Nested Loop",
                  "Output": [
                    "ci.person_id",
                    "t.title"
                  ],
                  "Parallel Aware": false,
                  "Parent Relationship": "Outer",
                  "Plan Rows": 1390,
                  "Plan Width": 21,
                  "Plans": [
                    {
                      "Actual Loops": 1,
                      "Actual Rows": 68316.0,
                      "Actual Startup Time": 4.046,
                      "Actual Total Time": 5136.646,
                      "Async Capable": false,
                      "Disabled": false,
                      "Inner Unique": true,
                      "Join Type": "Inner",
                      "Local Dirtied Blocks": 0,
                      "Local Hit Blocks": 0,
                      "Local Read Blocks": 0,
                      "Local Written Blocks": 0,
                      "Node Type": "Nested Loop",
                      "Output": [
                        "mc.movie_id",
                        "mk.movie_id",
                        "t.title",
                        "t.id"
                      ],
                      "Parallel Aware": false,
                      "Parent Relationship": "Outer",
                      "Plan Rows": 63,
                      "Plan Width": 29,
                      "Plans": [
                        {
                          "Actual Loops": 1,
                          "Actual Rows": 148552.0,
                          "Actual Startup Time": 3.735,
                          "Actual Total Time": 4742.876,
                          "Async Capable": false,
                          "Disabled": false,
                          "Inner Unique": false,
                          "Join Type": "Inner",
                          "Local Dirtied Blocks": 0,
                          "Local Hit Blocks": 0,
                          "Local Read Blocks": 0,
                          "Local Written Blocks": 0,
                          "Node Type": "Nested Loop",
                          "Output": [
                            "mk.movie_id",
                            "mc.movie_id",
                            "mc.company_id",
                            "t.title",
                            "t.id"
                          ],
                          "Parallel Aware": false,
                          "Parent Relationship": "Outer",
                          "Plan Rows": 173,
                          "Plan Width": 33,
                          "Plans": [
                            {
                              "Actual Loops": 1,
                              "Actual Rows": 41840.0,
                              "Actual Startup Time": 2.384,
                              "Actual Total Time": 3740.524,
                              "Async Capable": false,
                              "Disabled": false,
                              "Inner Unique": true,
                              "Join Type": "Inner",
                              "Local Dirtied Blocks": 0,
                              "Local Hit Blocks": 0,
                              "Local Read Blocks": 0,
                              "Local Written Blocks": 0,
                              "Node Type": "Nested Loop",
                              "Output": [
                                "mk.movie_id",
                                "t.title",
                                "t.id"
                              ],
                              "Parallel Aware": false,
                              "Parent Relationship": "Outer",
                              "Plan Rows": 34,
                              "Plan Width": 25,
                              "Plans": [
                                {
                                  "Actual Loops": 1,
                                  "Actual Rows": 41840.0,
                                  "Actual Startup Time": 1.809,
                                  "Actual Total Time": 25.059,
                                  "Async Capable": false,
                                  "Disabled": false,
                                  "Inner Unique": false,
                                  "Join Type": "Inner",
                                  "Local Dirtied Blocks": 0,
                                  "Local Hit Blocks": 0,
                                  "Local Read Blocks": 0,
                                  "Local Written Blocks": 0,
                                  "Node Type": "Nested Loop",
                                  "Output": [
                                    "mk.movie_id"
                                  ],
                                  "Parallel Aware": false,
                                  "Parent Relationship": "Outer",
                                  "Plan Rows": 34,
                                  "Plan Width": 4,
                                  "Plans": [
                                    {
                                      "Actual Loops": 1,
                                      "Actual Rows": 1.0,
                                      "Actual Startup Time": 1.213,
                                      "Actual Total Time": 1.235,
                                      "Alias": "k",
                                      "Async Capable": false,
                                      "Disabled": false,
                                      "Index Cond": "(k.keyword = 'character-name-in-title'::text)",
                                      "Index Name": "keyword_keyword",
                                      "Index Searches": 1,
                                      "Local Dirtied Blocks": 0,
                                      "Local Hit Blocks": 0,
                                      "Local Read Blocks": 0,
                                      "Local Written Blocks": 0,
                                      "Node Type": "Index Scan",
                                      "Output": [
                                        "k.id",
                                        "k.keyword",
                                        "k.phonetic_code"
                                      ],
                                      "Parallel Aware": false,
                                      "Parent Relationship": "Outer",
                                      "Plan Rows": 1,
                                      "Plan Width": 4,
                                      "Relation Name": "keyword",
                                      "Rows Removed by Index Recheck": 0,
                                      "Scan Direction": "Forward",
                                      "Schema": "job",
                                      "Shared Dirtied Blocks": 0,
                                      "Shared Hit Blocks": 1,
                                      "Shared Read Blocks": 3,
                                      "Shared Written Blocks": 0,
                                      "Startup Cost": 0.42,
                                      "Temp Read Blocks": 0,
                                      "Temp Written Blocks": 0,
                                      "Total Cost": 2.64
                                    },
                                    {
                                      "Actual Loops": 1,
                                      "Actual Rows": 41840.0,
                                      "Actual Startup Time": 0.592,
                                      "Actual Total Time": 18.136,
                                      "Alias": "mk",
                                      "Async Capable": false,
                                      "Disabled": false,
                                      "Heap Fetches": 17,
                                      "Index Cond": "(mk.keyword_id = k.id)",
                                      "Index Name": "keyword_id_movie_id_movie_keyword",
                                      "Index Searches": 1,
                                      "Local Dirtied Blocks": 0,
                                      "Local Hit Blocks": 0,
                                      "Local Read Blocks": 0,
                                      "Local Written Blocks": 0,
                                      "Node Type": "Index Only Scan",
                                      "Output": [
                                        "mk.keyword_id",
                                        "mk.movie_id"
                                      ],
                                      "Parallel Aware": false,
                                      "Parent Relationship": "Inner",
                                      "Plan Rows": 305,
                                      "Plan Width": 8,
                                      "Relation Name": "movie_keyword",
                                      "Rows Removed by Index Recheck": 0,
                                      "Scan Direction": "Forward",
                                      "Schema": "job",
                                      "Shared Dirtied Blocks": 0,
                                      "Shared Hit Blocks": 2,
                                      "Shared Read Blocks": 123,
                                      "Shared Written Blocks": 16,
                                      "Startup Cost": 0.43,
                                      "Temp Read Blocks": 0,
                                      "Temp Written Blocks": 0,
                                      "Total Cost": 7.97
                                    }
                                  ],
                                  "Shared Dirtied Blocks": 0,
                                  "Shared Hit Blocks": 3,
                                  "Shared Read Blocks": 126,
                                  "Shared Written Blocks": 16,
                                  "Startup Cost": 0.85,
                                  "Temp Read Blocks": 0,
                                  "Temp Written Blocks": 0,
                                  "Total Cost": 13.66
                                },
                                {
                                  "Actual Loops": 41840,
                                  "Actual Rows": 1.0,
                                  "Actual Startup Time": 0.088,
                                  "Actual Total Time": 0.088,
                                  "Alias": "t",
                                  "Async Capable": false,
                                  "Disabled": false,
                                  "Index Cond": "(t.id = mk.movie_id)",
                                  "Index Name": "dbprove_pk_title",
                                  "Index Searches": 41840,
                                  "Local Dirtied Blocks": 0,
                                  "Local Hit Blocks": 0,
                                  "Local Read Blocks": 0,
                                  "Local Written Blocks": 0,
                                  "Node Type": "Index Scan",
                                  "Output": [
                                    "t.id",
                                    "t.title",
                                    "t.imdb_index",
                                    "t.kind_id",
                                    "t.production_year",
                                    "t.imdb_id",
                                    "t.phonetic_code",
                                    "t.episode_of_id",
                                    "t.season_nr",
                                    "t.episode_nr",
                                    "t.series_years",
                                    "t.md5sum"
                                  ],
                                  "Parallel Aware": false,
                                  "Parent Relationship": "Inner",
                                  "Plan Rows": 1,
                                  "Plan Width": 21,
                                  "Relation Name": "title",
                                  "Rows Removed by Index Recheck": 0,
                                  "Scan Direction": "Forward",
                                  "Schema": "job",
                                  "Shared Dirtied Blocks": 0,
                                  "Shared Hit Blocks": 147477,
                                  "Shared Read Blocks": 19883,
                                  "Shared Written Blocks": 2005,
                                  "Startup Cost": 0.43,
                                  "Temp Read Blocks": 0,
                                  "Temp Written Blocks": 0,
                                  "Total Cost": 0.46
                                }
                              ],
                              "Shared Dirtied Blocks": 0,
                              "Shared Hit Blocks": 147480,
                              "Shared Read Blocks": 20009,
                              "Shared Written Blocks": 2021,
                              "Startup Cost": 1.28,
                              "Temp Read Blocks": 0,
                              "Temp Written Blocks": 0,
                              "Total Cost": 29.23
                            },
                            {
                              "Actual Loops": 41840,
                              "Actual Rows": 3.55,
                              "Actual Startup Time": 0.016,
                              "Actual Total Time": 0.023,
                              "Alias": "mc",
                              "Async Capable": false,
                              "Disabled": false,
                              "Index Cond": "(mc.movie_id = t.id)",
                              "Index Name": "movie_id_movie_companies",
                              "Index Searches": 41840,
                              "Local Dirtied Blocks": 0,
                              "Local Hit Blocks": 0,
                              "Local Read Blocks": 0,
                              "Local Written Blocks": 0,
                              "Node Type": "Index Scan",
                              "Output": [
                                "mc.id",
                                "mc.movie_id",
                                "mc.company_id",
                                "mc.company_type_id",
                                "mc.note"
                              ],
                              "Parallel Aware": false,
                              "Parent Relationship": "Inner",
                              "Plan Rows": 5,
                              "Plan Width": 8,
                              "Relation Name": "movie_companies",
                              "Rows Removed by Index Recheck": 0,
                              "Scan Direction": "Forward",
                              "Schema": "job",
                              "Shared Dirtied Blocks": 0,
                              "Shared Hit Blocks": 178872,
                              "Shared Read Blocks": 9389,
                              "Shared Written Blocks": 1429,
                              "Startup Cost": 0.43,
                              "Temp Read Blocks": 0,
                              "Temp Written Blocks": 0,
                              "Total Cost": 0.53
                            }
                          ],
                          "Shared Dirtied Blocks": 0,
                          "Shared Hit Blocks": 326352,
                          "Shared Read Blocks": 29398,
                          "Shared Written Blocks": 3450,
                          "Startup Cost": 1.71,
                          "Temp Read Blocks": 0,
                          "Temp Written Blocks": 0,
                          "Total Cost": 48.88
                        },
                        {
                          "Actual Loops": 148552,
                          "Actual Rows": 0.46,
                          "Actual Startup Time": 0.002,
                          "Actual Total Time": 0.002,
                          "Alias": "cn",
                          "Async Capable": false,
                          "Disabled": false,
                          "Filter": "(cn.country_code = '[us]'::text)",
                          "Index Cond": "(cn.id = mc.company_id)",
                          "Index Name": "dbprove_pk_company_name",
                          "Index Searches": 148552,
                          "Local Dirtied Blocks": 0,
                          "Local Hit Blocks": 0,
                          "Local Read Blocks": 0,
                          "Local Written Blocks": 0,
                          "Node Type": "Index Scan",
                          "Output": [
                            "cn.id",
                            "cn.name",
                            "cn.country_code",
                            "cn.imdb_id",
                            "cn.name_pcode_nf",
                            "cn.name_pcode_sf",
                            "cn.md5sum"
                          ],
                          "Parallel Aware": false,
                          "Parent Relationship": "Inner",
                          "Plan Rows": 1,
                          "Plan Width": 4,
                          "Relation Name": "company_name",
                          "Rows Removed by Filter": 1,
                          "Rows Removed by Index Recheck": 0,
                          "Scan Direction": "Forward",
                          "Schema": "job",
                          "Shared Dirtied Blocks": 0,
                          "Shared Hit Blocks": 593822,
                          "Shared Read Blocks": 386,
                          "Shared Written Blocks": 107,
                          "Startup Cost": 0.42,
                          "Temp Read Blocks": 0,
                          "Temp Written Blocks": 0,
                          "Total Cost": 0.44
                        }
                      ],
                      "Shared Dirtied Blocks": 0,
                      "Shared Hit Blocks": 920174,
                      "Shared Read Blocks": 29784,
                      "Shared Written Blocks": 3557,
                      "Startup Cost": 2.13,
                      "Temp Read Blocks": 0,
                      "Temp Written Blocks": 0,
                      "Total Cost": 125.27
                    },
                    {
                      "Actual Loops": 68316,
                      "Actual Rows": 41.46,
                      "Actual Startup Time": 0.013,
                      "Actual Total Time": 0.11,
                      "Alias": "ci",
                      "Async Capable": false,
                      "Disabled": false,
                      "Index Cond": "(ci.movie_id = t.id)",
                      "Index Name": "movie_id_cast_info",
                      "Index Searches": 68316,
                      "Local Dirtied Blocks": 0,
                      "Local Hit Blocks": 0,
                      "Local Read Blocks": 0,
                      "Local Written Blocks": 0,
                      "Node Type": "Index Scan",
                      "Output": [
                        "ci.id",
                        "ci.person_id",
                        "ci.movie_id",
                        "ci.person_role_id",
                        "ci.note",
                        "ci.nr_order",
                        "ci.role_id"
                      ],
                      "Parallel Aware": false,
                      "Parent Relationship": "Inner",
                      "Plan Rows": 40,
                      "Plan Width": 8,
                      "Relation Name": "cast_info",
                      "Rows Removed by Index Recheck": 0,
                      "Scan Direction": "Forward",
                      "Schema": "job",
                      "Shared Dirtied Blocks": 0,
                      "Shared Hit Blocks": 2914620,
                      "Shared Read Blocks": 34205,
                      "Shared Written Blocks": 4937,
                      "Startup Cost": 0.44,
                      "Temp Read Blocks": 0,
                      "Temp Written Blocks": 0,
                      "Total Cost": 1.27
                    }
                  ],
                  "Shared Dirtied Blocks": 0,
                  "Shared Hit Blocks": 3834794,
                  "Shared Read Blocks": 63989,
                  "Shared Written Blocks": 8494,
                  "Startup Cost": 2.57,
                  "Temp Read Blocks": 0,
                  "Temp Written Blocks": 0,
                  "Total Cost": 230.21
                },
                {
                  "Actual Loops": 2832555,
                  "Actual Rows": 1.0,
                  "Actual Startup Time": 0.001,
                  "Actual Total Time": 0.001,
                  "Alias": "n",
                  "Async Capable": false,
                  "Disabled": false,
                  "Heap Fetches": 135,
                  "Index Cond": "(n.id = ci.person_id)",
                  "Index Name": "dbprove_pk_name",
                  "Index Searches": 2832555,
                  "Local Dirtied Blocks": 0,
                  "Local Hit Blocks": 0,
                  "Local Read Blocks": 0,
                  "Local Written Blocks": 0,
                  "Node Type": "Index Only Scan",
                  "Output": [
                    "n.id"
                  ],
                  "Parallel Aware": false,
                  "Parent Relationship": "Inner",
                  "Plan Rows": 1,
                  "Plan Width": 4,
                  "Relation Name": "name",
                  "Rows Removed by Index Recheck": 0,
                  "Scan Direction": "Forward",
                  "Schema": "job",
                  "Shared Dirtied Blocks": 0,
                  "Shared Hit Blocks": 9093816,
                  "Shared Read Blocks": 0,
                  "Shared Written Blocks": 0,
                  "Startup Cost": 0.43,
                  "Temp Read Blocks": 0,
                  "Temp Written Blocks": 0,
                  "Total Cost": 0.45
                }
              ],
              "Shared Dirtied Blocks": 0,
              "Shared Hit Blocks": 12928610,
              "Shared Read Blocks": 63989,
              "Shared Written Blocks": 8494,
              "Startup Cost": 3.0,
              "Temp Read Blocks": 0,
              "Temp Written Blocks": 0,
              "Total Cost": 852.72
            },
            {
              "Actual Loops": 2832555,
              "Actual Rows": 1.31,
              "Actual Startup Time": 0.001,
              "Actual Total Time": 0.001,
              "Alias": "an",
              "Async Capable": false,
              "Disabled": false,
              "Index Cond": "(an.person_id = n.id)",
              "Index Name": "person_id_aka_name",
              "Index Searches": 2832555,
              "Local Dirtied Blocks": 0,
              "Local Hit Blocks": 0,
              "Local Read Blocks": 0,
              "Local Written Blocks": 0,
              "Node Type": "Index Scan",
              "Output": [
                "an.id",
                "an.person_id",
                "an.name",
                "an.imdb_index",
                "an.name_pcode_cf",
                "an.name_pcode_nf",
                "an.surname_pcode",
                "an.md5sum"
              ],
              "Parallel Aware": false,
              "Parent Relationship": "Inner",
              "Plan Rows": 2,
              "Plan Width": 20,
              "Relation Name": "aka_name",
              "Rows Removed by Index Recheck": 0,
              "Scan Direction": "Forward",
              "Schema": "job",
              "Shared Dirtied Blocks": 0,
              "Shared Hit Blocks": 10602528,
              "Shared Read Blocks": 42,
              "Shared Written Blocks": 2,
              "Startup Cost": 0.42,
              "Temp Read Blocks": 0,
              "Temp Written Blocks": 0,
              "Total Cost": 0.46
            }
          ],
          "Shared Dirtied Blocks": 0,
          "Shared Hit Blocks": 23531138,
          "Shared Read Blocks": 64031,
          "Shared Written Blocks": 8496,
          "Startup Cost": 3.43,
          "Temp Read Blocks": 0,
          "Temp Written Blocks": 0,
          "Total Cost": 1524.88
        }
      ],
      "Shared Dirtied Blocks": 0,
      "Shared Hit Blocks": 23531138,
      "Shared Read Blocks": 64031,
      "Shared Written Blocks": 8496,
      "Startup Cost": 1541.76,
      "Strategy": "Plain",
      "Temp Read Blocks": 0,
      "Temp Written Blocks": 0,
      "Total Cost": 1541.77
    },
    "Planning": {
      "Local Dirtied Blocks": 0,
      "Local Hit Blocks": 0,
      "Local Read Blocks": 0,
      "Local Written Blocks": 0,
      "Shared Dirtied Blocks": 0,
      "Shared Hit Blocks": 139,
      "Shared Read Blocks": 48,
      "Shared Written Blocks": 0,
      "Temp Read Blocks": 0,
      "Temp Written Blocks": 0
    },
    "Planning Time": 32.805,
    "Triggers": []
  }
]